{
    "interactionModel": {
        "languageModel": {
            "invocationName": "la frase diaria",
            "intents": [
                {
                    "name": "AMAZON.CancelIntent",
                    "samples": [
                        "cancel"
                    ]
                },
                {
                    "name": "AMAZON.HelpIntent",
                    "samples": [
                        "help"
                    ]
                },
                {
                    "name": "AMAZON.StopIntent",
                    "samples": [
                        "stop"
                    ]
                },
                {
                    "name": "AMAZON.NavigateHomeIntent",
                    "samples": []
                }
            ],
            "types": []
        }
    }
}